AUTHORS
CHANGELOG.rst
LICENSE
MANIFEST.in
README
README.rst
requirements.txt
setup.cfg
setup.py
docs/CHANGELOG.rst
docs/CONTRIBUTING.rst
docs/LICENSE.rst
docs/README.rst
docs/conf.py
docs/index.rst
docs/html/index.html
pysol_cards/__init__.py
pysol_cards/cards.py
pysol_cards/cwrap.py
pysol_cards/deal_game.py
pysol_cards/errors.py
pysol_cards/gen_multi_cli.py
pysol_cards/random.py
pysol_cards/random_base.py
pysol_cards/single_deal_args_parse.py
pysol_cards.egg-info/PKG-INFO
pysol_cards.egg-info/SOURCES.txt
pysol_cards.egg-info/dependency_links.txt
pysol_cards.egg-info/not-zip-safe
pysol_cards.egg-info/top_level.txt
tests/test_pysol_cards.py
tests/test_pysol_cwrap.py